ctodd_python_lib_general-1.0.2.dist-info/LICENSE.txt
ctodd_python_lib_general-1.0.2.dist-info/METADATA
ctodd_python_lib_general-1.0.2.dist-info/RECORD
ctodd_python_lib_general-1.0.2.dist-info/WHEEL
ctodd_python_lib_general-1.0.2.dist-info/top_level.txt
general_helpers/__init__.py
general_helpers/downloader.py
general_helpers/user_input_helpers.py
general_helpers/tests/__init__.py
general_helpers/tests/test_downloader.py
general_helpers/tests/test_user_input_helpers.py
